pybluebox/__init__.py
pybluebox-0.1.0.dist-info/licenses/LICENSE
pybluebox-0.1.0.dist-info/METADATA
pybluebox-0.1.0.dist-info/WHEEL
pybluebox-0.1.0.dist-info/top_level.txt
pybluebox-0.1.0.dist-info/RECORD
