Metadata-Version: 2.4
Name: pybluebox
Version: 0.1.0
Summary: A Python toolkit for fisheries modeling and simulation.
Home-page: https://github.com/INTELLIGENTICA/PyBlueBox
Author: Abdelouahed Ben Mhamed
Author-email: Abdelouahed Ben Mhamed <a.benmhamed@intelligentica.net>
Project-URL: Homepage, https://github.com/INTELLIGENTICA/PyBlueBox
Project-URL: Repository, https://github.com/INTELLIGENTICA/PyBlueBox
Classifier: Programming Language :: Python :: 3
Classifier: License :: OSI Approved :: MIT License
Classifier: Operating System :: OS Independent
Requires-Python: >=3.7
License-File: LICENSE
Dynamic: license-file
